electronbonder/__init__.py
electronbonder/client.py
tests/__init__.py
tests/test_client.py
ElectronBonder-2.2.dist-info/METADATA
ElectronBonder-2.2.dist-info/WHEEL
ElectronBonder-2.2.dist-info/top_level.txt
ElectronBonder-2.2.dist-info/RECORD
