Metadata-Version: 2.1
Name: ElectronBonder
Version: 2.2
Summary: Project Electron Client Library
Home-page: https://github.com/RockefellerArchiveCenter/ElectronBonder
Author: Rockefeller Archive Center
Author-email: archive@rockarch.org
License: MIT
Classifier: Programming Language :: Python :: 3
Classifier: Intended Audience :: Other Audience
Classifier: License :: OSI Approved :: MIT License
Requires-Python: >=3.10
Requires-Dist: requests
Requires-Dist: requests-oauthlib
Requires-Dist: six
